{
  "data": {
    "attributes": {
      "quote-intent": {
        "Payment": null,
        "ClientData":null,
        "Address": {
          "AddressLine1": "10505 lone pine ln",
          "AddressLine2": "",
          "AddressType": null,
          "City": "Fort Worth",
          "Country": null,
          "Counties": [{
            "Name": "Parker",
            "StateAbbreviation": "TX"
          },
            {
              "Name": "Tarrant",
              "StateAbbreviation": "TX"
            }],
          "County": "Parker",
          "ID": "7e6f2d00-b8a6-4175-37e1-4f1d5ce7377f",
          "PostalCode": "76108",
          "State": "TX",
          "IsValidated": true,
          "HasRatedLocations": true
        },
        "Ancillaries": {
          "AncillaryPlans": [],
          "AncillaryResponse": null,
          "ParamContent": null
        },
        "Drivers": [{
          "AgeFirstLicensed": "16",
          "CurrentInsuranceStatus": "just_acquired_auto",
          "CurrentInsurer": "",
          "CurrentlyInsured": false,
          "CurrentProviderPremium": null,
          "CurrentStudentEnrollment": null,
          "CurrentlyEnrolled": null,
          "CurrentZipCode": "Yes",
          "DateOfBirth": "12-10-1970",
          "DateOfResidence": "01-01-2011",
          "DrivesAnyVehicles": null,
          "EmailAddress": "fun@fun.com",
          "EmailAddressConfirm": null,
          "EmploymentStatus": "HomeMaker",
          "FirstName": "Lisa",
          "Gender": "F",
          "GoodStudentDiscount": false,
          "HighestEducationLevel": "bachelors",
          "ID": "885848a9-67ae-b19d-c7eb-f23e60a7153c",
          "Incidents": [],
          "LastName": "Todd",
          "LicenseNumber": "",
          "LicenseState": "",
          "LicenseStatus": "valid",
          "MaritalStatus": "M",
          "MiddleName": "",
          "MilitaryBranch": "",
          "MilitaryStatus": "",
          "MonthSelected": null,
          "NumberOfCreditPulls": null,
          "Occupation": "424",
          "OwnsOwnVehicle": null,
          "PhoneNumber": "5635345345",
          "PreviousLapse": "",
          "PrimaryDriver": true,
          "PrimaryInsured": null,
          "PrimaryVehicleID": "58718ec8-01c1-41e9-fc41-c9062b794541",
          "ProcessingId": null,
          "RatingStatus": "rated",
          "RelationshipToInsured": "applicant",
          "ResidenceOwnership": "home",
          "Retired": null,
          "SocialSecurityNumber": null,
          "Suffix": "",
          "Title": null,
          "YearsAtCurrentResidence": null,
          "YearSelected": 1,
          "YearsWithCurrentInsurer": "",
          "DrivesAnyListedVehicles": false,
          "HasDriversSafetyCourse": false,
          "IsAuthorizedUser": false,
          "LivesInHousehold": false,
          "PCID": "",
          "SingleSearchHash": "6dec4a876d6f13773920ad98bc24ae0226ed0b33"
        },
          {
            "AgeFirstLicensed": "16",
            "CurrentInsuranceStatus": "",
            "CurrentInsurer": "",
            "CurrentlyInsured": false,
            "CurrentProviderPremium": null,
            "CurrentStudentEnrollment": null,
            "CurrentlyEnrolled": null,
            "CurrentZipCode": null,
            "DateOfBirth": "12-14-1971",
            "DateOfResidence": "",
            "DrivesAnyVehicles": null,
            "EmailAddress": "",
            "EmailAddressConfirm": null,
            "EmploymentStatus": "EmployedPrivately",
            "FirstName": "Carl",
            "Gender": "M",
            "GoodStudentDiscount": false,
            "HighestEducationLevel": "highschool",
            "ID": "6a4da93f-750d-75d7-cde4-096f4d66f4d5",
            "Incidents": [],
            "LastName": "Todd",
            "LicenseNumber": "",
            "LicenseState": "",
            "LicenseStatus": "valid",
            "MaritalStatus": "M",
            "MiddleName": "",
            "MilitaryBranch": "",
            "MilitaryStatus": "",
            "MonthSelected": null,
            "NumberOfCreditPulls": null,
            "Occupation": "64",
            "OwnsOwnVehicle": null,
            "PhoneNumber": "",
            "PreviousLapse": "",
            "PrimaryDriver": false,
            "PrimaryInsured": null,
            "PrimaryVehicleID": "0331126c-f790-87d7-34f3-0e9892fade40",
            "ProcessingId": null,
            "RatingStatus": "rated",
            "RelationshipToInsured": "spouse",
            "ResidenceOwnership": "",
            "Retired": null,
            "SocialSecurityNumber": null,
            "Suffix": "",
            "Title": null,
            "YearsAtCurrentResidence": null,
            "YearSelected": null,
            "YearsWithCurrentInsurer": "",
            "DrivesAnyListedVehicles": true,
            "HasDriversSafetyCourse": false,
            "IsAuthorizedUser": false,
            "LivesInHousehold": false,
            "PCID": "",
            "SingleSearchHash": ""
          }],
        "Vehicles": [{
          "AntiTheftDevice": false,
          "AvailableCoverages": [],
          "BrandedTitle": false,
          "CostWhenNew": null,
          "CurrentOwner": false,
          "CustomEquipment": null,
          "DamageDescription": "",
          "DateOfAcquisition": "01-01-2013",
          "DiminishingDeductibleFee": null,
          "EstimatedAnnualMileage": "8000_to_9999",
          "Fees": [],
          "HasDiminishingDeductible": false,
          "ID": "58718ec8-01c1-41e9-fc41-c9062b794541",
          "IsDamaged": null,
          "Lienholder": {
            "AddressLine1": "",
            "AddressLine2": "",
            "City": "",
            "Country": "",
            "County": "",
            "Name": "",
            "PostalCode": "",
            "State": ""
          },
          "Make": "Ford",
          "MakeID": 22,
          "Model": "ESCAPE XLS",
          "ModelID": 2997,
          "MonthSelected": null,
          "Ownership": "PaidOff",
          "PrimaryDriverID": "6a4da93f-750d-75d7-cde4-096f4d66f4d5",
          "RegistrationState": null,
          "ShortModelName": "ESCAPE",
          "Style": "UTL4X24D 4 cyl",
          "PrimaryUse": "commuting",
          "ValueOfCustomEquipment": "",
          "Vin": "",
          "Year": "2010",
          "YearsVehicleOwned": "",
          "YearSelected": 1,
          "YearStyleID": 25111,
          "IgnoreVIN": false,
          "LicenseState": "",
          "PCID": "",
          "Salvaged": false
        },
          {
            "AntiTheftDevice": false,
            "AvailableCoverages": [],
            "BrandedTitle": false,
            "CostWhenNew": null,
            "CurrentOwner": false,
            "CustomEquipment": null,
            "DamageDescription": "",
            "DateOfAcquisition": "01-01-2013",
            "DiminishingDeductibleFee": null,
            "EstimatedAnnualMileage": "6000_to_7999",
            "Fees": [],
            "HasDiminishingDeductible": false,
            "ID": "0331126c-f790-87d7-34f3-0e9892fade40",
            "IsDamaged": null,
            "Lienholder": {
              "AddressLine1": "",
              "AddressLine2": "",
              "City": "",
              "Country": "",
              "County": "",
              "Name": "",
              "PostalCode": "",
              "State": ""
            },
            "Make": "Ford",
            "MakeID": 22,
            "Model": "TAURUS GL",
            "ModelID": 818,
            "MonthSelected": null,
            "Ownership": "PaidOff",
            "PrimaryDriverID": "6a4da93f-750d-75d7-cde4-096f4d66f4d5",
            "RegistrationState": null,
            "ShortModelName": "TAURUS GL",
            "Style": "SEDAN 4D 6 cyl",
            "PrimaryUse": "commuting",
            "ValueOfCustomEquipment": "",
            "Vin": "",
            "Year": "1998",
            "YearsVehicleOwned": "",
            "YearSelected": 1,
            "YearStyleID": 40266,
            "IgnoreVIN": false,
            "LicenseState": "",
            "PCID": "",
            "Salvaged": false
          }],
        "Policy": {
          "IsUWPhotoReviewExist": null,
          "EffectiveDate": "05-11-2016",
          "OrigPolicyStartDate": null,
          "PolicyStatus": "",
          "MVRClueCalled": false,
          "WrittenDate": null,
          "BadDebtsFlag": null,
          "MaterialMisrep": null,
          "HasMotorcycle": false,
          "TerritoryRestriction": false,
          "PolicyNumber": null,
          "CurrentInsuranceLimits": null,
          "AvailableCoverages": null,
          "AccountNumber": "",
          "JobNumber": ""
        },
        "Quote": {
          "Discounts": [{
            "Desc": "Electronic Signature",
            "SortOrder": 1,
            "Value": "electronicsignature"
          },
            {
              "Desc": "Online",
              "SortOrder": 2,
              "Value": "online"
            },
            {
              "Desc": "Paperless",
              "SortOrder": 3,
              "Value": "paperless"
            },
            {
              "Desc": "Home Owner",
              "SortOrder": 4,
              "Value": "homeowner"
            },
            {
              "Desc": "Multi Car",
              "SortOrder": 6,
              "Value": "multicar"
            }],
          "PayPlans": null,
          "PremiumFees": [{
            "Desc": null,
            "Amount": null
          }],
          "QuoteNumber": "XVY5Q95MZ",
          "TotalFees": "0",
          "TotalPremium": "0",
          "TotalPremiumWithFees": "0",
          "PreviousTotalPremiumWithFees": null,
          "Fees": null
        },
        "QuoteState": {
          "AdditionalDrivers": "Yes",
          "HasRatedLocations": false,
          "HasIncidents": false,
          "HasConvictions": "No",
          "HasDmsRun": false,
          "DmsConfirmation": false,
          "MVRClueCalled": false,
          "DriverConvictions": [],
          "BindAttempts": 0,
          "PreviousTotalPremiumWithFees": null
        }
      }
    }
  }
}
